byteai/__init__.py
byteai/client.py
byteai/payment.py
byteai/test_tokenizer.py
byteai/tokenizer.py
byteai-0.1.4.dist-info/METADATA
byteai-0.1.4.dist-info/WHEEL
byteai-0.1.4.dist-info/top_level.txt
byteai-0.1.4.dist-info/RECORD
