Metadata-Version: 2.1
Name: byteai
Version: 0.1.4
Summary: AI development tools
Author: Aaron Jerez
Author-email: aaronjerez1@gmail.com
Requires-Dist: tiktoken
Requires-Dist: stripe
Requires-Dist: aiohttp
Requires-Dist: numpy
